LICENSE
MANIFEST.in
README.rst
setup.py
django_static_autocollect.egg-info/PKG-INFO
django_static_autocollect.egg-info/SOURCES.txt
django_static_autocollect.egg-info/dependency_links.txt
django_static_autocollect.egg-info/not-zip-safe
django_static_autocollect.egg-info/requires.txt
django_static_autocollect.egg-info/top_level.txt
static_autocollect/__init__.py
static_autocollect/apps.py
static_autocollect/management/__init__.py
static_autocollect/management/commands/__init__.py
static_autocollect/management/commands/watch_static.py